openpibo_detect_models/__init__.py
openpibo_detect_models/models/efficientnet_labels.txt
openpibo_detect_models/models/efficientnet_lite3.tflite
openpibo_detect_models/models/frozen_inference_graph.pb
openpibo_detect_models/models/movenet_lightning.tflite
openpibo_detect_models/models/ssd_mobilenet_v2_coco_2018_03_29.pbtxt
openpibo_detect_models-0.4.4.dist-info/METADATA
openpibo_detect_models-0.4.4.dist-info/WHEEL
openpibo_detect_models-0.4.4.dist-info/top_level.txt
openpibo_detect_models-0.4.4.dist-info/RECORD
